oneliner.py
oneliner-0.3.1.dist-info/LICENSE
oneliner-0.3.1.dist-info/METADATA
oneliner-0.3.1.dist-info/WHEEL
oneliner-0.3.1.dist-info/entry_points.txt
oneliner-0.3.1.dist-info/top_level.txt
oneliner-0.3.1.dist-info/RECORD
