Metadata-Version: 2.1
Name: oneliner
Version: 0.3.1
Summary: practical python one-liners
Author-email: Georgi Valkov <georgi.t.valkov@gmail.com>
License: Copyright (c) 2012-2024 Georgi Valkov. All rights reserved.
Project-URL: Homepage, https://github.com/gvalkov/python-oneliner
Keywords: oneliner,one-liner
Classifier: Development Status :: 3 - Alpha
Classifier: Programming Language :: Python :: 3
Classifier: License :: OSI Approved :: BSD License
Classifier: Environment :: Console
Classifier: Intended Audience :: Developers
Classifier: Intended Audience :: System Administrators
Classifier: Operating System :: POSIX :: Linux
Requires-Python: >=3.6
License-File: LICENSE
